stalin_sort/__init__.py
stalin_sort-0.1.dist-info/LICENSE
stalin_sort-0.1.dist-info/METADATA
stalin_sort-0.1.dist-info/WHEEL
stalin_sort-0.1.dist-info/top_level.txt
stalin_sort-0.1.dist-info/RECORD
