Metadata-Version: 2.1
Name: stalin-sort
Version: 0.1
Summary: Stalin Sort is an efficient sorting algorithm, serving as a systematic method for placing the elements of a random access file or an array in order.
Home-page: http://github.com/paszymaja/stalin_sort
Author: Paszymaja
Author-email: sprzepiora@hotmail.co.uk
License: MIT
Platform: UNKNOWN
